bit_collision_free_MF/__init__.py
bit_collision_free_MF/__version__.py
bit_collision_free_MF/fingerprint.py
bit_collision_free_MF/utils.py
bit_collision_free_mf-0.8.0.dist-info/licenses/LICENSE
bit_collision_free_mf-0.8.0.dist-info/METADATA
bit_collision_free_mf-0.8.0.dist-info/WHEEL
bit_collision_free_mf-0.8.0.dist-info/top_level.txt
bit_collision_free_mf-0.8.0.dist-info/RECORD
