Metadata-Version: 2.4
Name: bit_collision_free_MF
Version: 0.8.0
Summary: Generate molecular fingerprints with guaranteed collision‑free bits.
Author-email: Shifa Zhong <sfzhong@tongji.edu.cn>, Jibai Li <51263903065@stu.ecnu.edu.cn>
License: MIT License
Project-URL: Homepage, https://github.com/Shifa-Zhong/bit_collision_free_MF
Project-URL: Documentation, https://Shifa-Zhong.github.io/bit_collision_free_MF
Classifier: License :: OSI Approved :: MIT License
Classifier: Development Status :: 3 - Alpha
Classifier: Intended Audience :: Science/Research
Classifier: Topic :: Scientific/Engineering :: Chemistry
Classifier: Programming Language :: Python :: 3
Classifier: Programming Language :: Python :: 3.9
Classifier: Programming Language :: Python :: 3.10
Classifier: Programming Language :: Python :: 3.11
Classifier: Programming Language :: Python :: 3.12
Classifier: Operating System :: OS Independent
Requires-Python: >=3.9
License-File: LICENSE
Requires-Dist: numpy>=1.24
Requires-Dist: pandas>=2.0
Requires-Dist: rdkit
Dynamic: license-file
